PythonDocxAJM/DocConfig.py
PythonDocxAJM/PythonDocxAJM.py
PythonDocxAJM/__init__.py
PythonDocxAJM/_version.py
pythondocxajm-0.1.6.dist-info/licenses/LICENSE.txt
pythondocxajm-0.1.6.dist-info/METADATA
pythondocxajm-0.1.6.dist-info/WHEEL
pythondocxajm-0.1.6.dist-info/top_level.txt
pythondocxajm-0.1.6.dist-info/RECORD
